scicommander/__init__.py
scicommander/scicmd.py
scicommander-0.3.3.data/scripts/scishell
scicommander-0.3.3.dist-info/METADATA
scicommander-0.3.3.dist-info/WHEEL
scicommander-0.3.3.dist-info/entry_points.txt
scicommander-0.3.3.dist-info/top_level.txt
scicommander-0.3.3.dist-info/RECORD
